MLRsearch/__init__.py
MLRsearch/candidate.py
MLRsearch/config.py
MLRsearch/discrete_interval.py
MLRsearch/discrete_load.py
MLRsearch/discrete_result.py
MLRsearch/discrete_width.py
MLRsearch/expander.py
MLRsearch/global_width.py
MLRsearch/goal_result.py
MLRsearch/limit_handler.py
MLRsearch/load_rounding.py
MLRsearch/load_stats.py
MLRsearch/measurement_database.py
MLRsearch/multiple_loss_ratio_search.py
MLRsearch/relevant_bounds.py
MLRsearch/search_goal.py
MLRsearch/search_goal_tuple.py
MLRsearch/selector.py
MLRsearch/target_scaling.py
MLRsearch/target_spec.py
MLRsearch/target_stat.py
MLRsearch/trimmed_stat.py
MLRsearch/dataclass/__init__.py
MLRsearch/dataclass/dc_property.py
MLRsearch/dataclass/field.py
MLRsearch/pep3140/__init__.py
MLRsearch/pep3140/classes.py
MLRsearch/strategy/__init__.py
MLRsearch/strategy/base.py
MLRsearch/strategy/bisect.py
MLRsearch/strategy/extend_hi.py
MLRsearch/strategy/extend_lo.py
MLRsearch/strategy/halve.py
MLRsearch/strategy/refine_hi.py
MLRsearch/strategy/refine_lo.py
MLRsearch/trial_measurement/__init__.py
MLRsearch/trial_measurement/abstract_measurer.py
MLRsearch/trial_measurement/measurement_result.py
MLRsearch-1.2.1.dist-info/LICENSE.txt
MLRsearch-1.2.1.dist-info/METADATA
MLRsearch-1.2.1.dist-info/WHEEL
MLRsearch-1.2.1.dist-info/top_level.txt
MLRsearch-1.2.1.dist-info/RECORD
