Metadata-Version: 2.1
Name: MLRsearch
Version: 1.2.1
Summary: Library for extending and speeding up througput search.
Author-email: "Cisco Systems Inc. and/or its affiliates" <csit-dev@lists.fd.io>
Maintainer-email: Vratko Polak <vrpolak@cisco.com>, Tibor Frank <tifrank@cisco.com>
License: Apache License
Project-URL: Bug Tracker, https://jira.fd.io/projects/CSIT/issues
Project-URL: Source, https://gerrit.fd.io/r/gitweb?p=csit.git;a=tree;f=PyPI/MLRsearch
Keywords: binary search,throughput,networking,RFC 2544,conditional throughput
Classifier: Development Status :: 3 - Alpha
Classifier: Intended Audience :: Telecommunications Industry
Classifier: License :: OSI Approved :: Apache Software License
Classifier: Natural Language :: English
Classifier: Operating System :: OS Independent
Classifier: Programming Language :: Python :: 3.8
Classifier: Topic :: System :: Networking
Requires-Python: ~=3.8
License-File: LICENSE.txt
